django_github_sso/__init__.py
django_github_sso/admin.py
django_github_sso/apps.py
django_github_sso/checks/__init__.py
django_github_sso/checks/warnings.py
django_github_sso/conf.py
django_github_sso/helpers.py
django_github_sso/hooks.py
django_github_sso/main.py
django_github_sso/migrations/0001_initial.py
django_github_sso/migrations/__init__.py
django_github_sso/models.py
django_github_sso/static/django_github_sso/github_button.css
django_github_sso/templates/github_sso/login.html
django_github_sso/templates/github_sso/login_sso.html
django_github_sso/templatetags/__init__.py
django_github_sso/templatetags/show_form.py
django_github_sso/templatetags/sso_tags.py
django_github_sso/tests/__init__.py
django_github_sso/tests/conftest.py
django_github_sso/tests/test_callables.py
django_github_sso/tests/test_conf.py
django_github_sso/tests/test_github_auth.py
django_github_sso/tests/test_models.py
django_github_sso/tests/test_sites.py
django_github_sso/tests/test_tags.py
django_github_sso/tests/test_user_helper.py
django_github_sso/tests/test_views.py
django_github_sso/urls.py
django_github_sso/utils.py
django_github_sso/views.py
django_github_sso-5.0.2.dist-info/METADATA
django_github_sso-5.0.2.dist-info/WHEEL
django_github_sso-5.0.2.dist-info/licenses/LICENSE
django_github_sso-5.0.2.dist-info/RECORD
