Metadata-Version: 2.4
Name: django-github-sso
Version: 5.0.2
Summary: Easily add GitHub Authentication to your Django Projects
License: MIT
License-File: LICENSE
Keywords: github,django,sso
Author: Chris Maillefaud
Author-email: chrismaille@users.noreply.github.com
Requires-Python: >=3.11,<4.0
Classifier: Development Status :: 4 - Beta
Classifier: Environment :: Plugins
Classifier: Framework :: Django
Classifier: Framework :: Django :: 4.2
Classifier: Framework :: Django :: 5.0
Classifier: Framework :: Django :: 5.1
Classifier: Framework :: Django :: 5.2
Classifier: Intended Audience :: Developers
Classifier: License :: OSI Approved :: MIT License
Classifier: Programming Language :: Python :: 3
Classifier: Programming Language :: Python :: 3.11
Classifier: Programming Language :: Python :: 3.12
Classifier: Programming Language :: Python :: 3.13
Classifier: Programming Language :: Python :: 3.14
Requires-Dist: PyGithub
Requires-Dist: django (>=4.2)
Requires-Dist: httpx
Requires-Dist: loguru
Requires-Dist: requests-oauthlib
Project-URL: Repository, https://github.com/megalus/django-github-sso
